CHANGES.txt
COPYRIGHT.txt
LICENSE.txt
MANIFEST.in
README.txt
TODO.txt
bootstrap.py
buildout.cfg
setup.py
src/z3c/__init__.py
src/z3c.json.egg-info/PKG-INFO
src/z3c.json.egg-info/SOURCES.txt
src/z3c.json.egg-info/dependency_links.txt
src/z3c.json.egg-info/namespace_packages.txt
src/z3c.json.egg-info/not-zip-safe
src/z3c.json.egg-info/requires.txt
src/z3c.json.egg-info/top_level.txt
src/z3c/json/README.txt
src/z3c/json/__init__.py
src/z3c/json/configure.zcml
src/z3c/json/converter.py
src/z3c/json/exceptions.py
src/z3c/json/interfaces.py
src/z3c/json/minjson.py
src/z3c/json/proxy.py
src/z3c/json/testing.py
src/z3c/json/tests.py
src/z3c/json/transport.py
src/z3c/json/z3c.json-configure.zcml